CHANGELOG.rst
LICENSE.rst
MANIFEST.in
README.rst
setup.py
wagtailtinymce/__init__.py
wagtailtinymce/apps.py
wagtailtinymce/models.py
wagtailtinymce/rich_text.py
wagtailtinymce/wagtail_hooks.py
wagtailtinymce.egg-info/PKG-INFO
wagtailtinymce.egg-info/SOURCES.txt
wagtailtinymce.egg-info/dependency_links.txt
wagtailtinymce.egg-info/entry_points.txt
wagtailtinymce.egg-info/not-zip-safe
wagtailtinymce.egg-info/pbr.json
wagtailtinymce.egg-info/requires.txt
wagtailtinymce.egg-info/top_level.txt
wagtailtinymce/static/wagtailtinymce/css/icons.css
wagtailtinymce/static/wagtailtinymce/js/tinymce-editor.js
wagtailtinymce/static/wagtailtinymce/js/tinymce-plugins/wagtaildoclink.js
wagtailtinymce/static/wagtailtinymce/js/tinymce-plugins/wagtailembeds.js
wagtailtinymce/static/wagtailtinymce/js/tinymce-plugins/wagtailimage.js
wagtailtinymce/static/wagtailtinymce/js/tinymce-plugins/wagtaillink.js
wagtailtinymce/static/wagtailtinymce/js/tinymce-plugins/langs/af.js
wagtailtinymce/static/wagtailtinymce/js/tinymce-plugins/langs/ar.js
wagtailtinymce/static/wagtailtinymce/js/tinymce-plugins/langs/ast.js
wagtailtinymce/static/wagtailtinymce/js/tinymce-plugins/langs/az.js
wagtailtinymce/static/wagtailtinymce/js/tinymce-plugins/langs/be.js
wagtailtinymce/static/wagtailtinymce/js/tinymce-plugins/langs/bg.js
wagtailtinymce/static/wagtailtinymce/js/tinymce-plugins/langs/bn.js
wagtailtinymce/static/wagtailtinymce/js/tinymce-plugins/langs/br.js
wagtailtinymce/static/wagtailtinymce/js/tinymce-plugins/langs/bs.js
wagtailtinymce/static/wagtailtinymce/js/tinymce-plugins/langs/ca.js
wagtailtinymce/static/wagtailtinymce/js/tinymce-plugins/langs/cs.js
wagtailtinymce/static/wagtailtinymce/js/tinymce-plugins/langs/cy.js
wagtailtinymce/static/wagtailtinymce/js/tinymce-plugins/langs/da.js
wagtailtinymce/static/wagtailtinymce/js/tinymce-plugins/langs/de.js
wagtailtinymce/static/wagtailtinymce/js/tinymce-plugins/langs/de_CH.js
wagtailtinymce/static/wagtailtinymce/js/tinymce-plugins/langs/el.js
wagtailtinymce/static/wagtailtinymce/js/tinymce-plugins/langs/en.js
wagtailtinymce/static/wagtailtinymce/js/tinymce-plugins/langs/en_AU.js
wagtailtinymce/static/wagtailtinymce/js/tinymce-plugins/langs/en_GB.js
wagtailtinymce/static/wagtailtinymce/js/tinymce-plugins/langs/eo.js
