Metadata-Version: 1.1
Name: wagtailtinymce
Version: 4.2.1.5
Summary: A TinyMCE editor integration for Wagtail
Home-page: https://github.com/isotoma/wagtailtinymce.git
Author: Richard Mitchell
Author-email: richard.mitchell@isotoma.com
License: New BSD
Platform: UNKNOWN
Classifier: Development Status :: 5 - Production/Stable
Classifier: Environment :: Web Environment
Classifier: Intended Audience :: Developers
Classifier: License :: OSI Approved :: BSD License
Classifier: Operating System :: OS Independent
Classifier: Programming Language :: Python
Classifier: Programming Language :: Python :: 2
Classifier: Programming Language :: Python :: 2.7
Classifier: Programming Language :: Python :: 3
Classifier: Programming Language :: Python :: 3.3
Classifier: Programming Language :: Python :: 3.4
Classifier: Programming Language :: Python :: 3.5
Classifier: Framework :: Django
Classifier: Framework :: Django :: 1.8
Classifier: Framework :: Django :: 1.9
Classifier: Topic :: Internet :: WWW/HTTP :: Site Management
